<?xml version="1.0" encoding="UTF-8"?>
<addon
  id="webinterface.tofu"
  version="0.1.0"
  name="TOFU"
  provider-name="Pivos Technology Group">
  <requires>
    <import addon="xbmc.json" version="6.0.0"/>
  </requires>
  <extension
    point="xbmc.gui.webinterface"/>
  <extension point="xbmc.addon.metadata">
    <summary lang="af">(TOFU se verstek web koppelvlak)</summary>
    <summary lang="am">(የ TOFU ነባር የዌብ ገጽታዎች)</summary>
    <summary lang="ar">(واجهه الشبكة العنكبوتية المبدئية لـ توفو)</summary>
    <summary lang="be">(TOFU's default web interface)</summary>
    <summary lang="bg">(стандартният уеб интерфейс на TOFU)</summary>
    <summary lang="ca">(Interficie web per defecte del TOFU)</summary>
    <summary lang="cs">(Výchozí webové rozhraní TOFU).</summary>
    <summary lang="cy">(Rhyngwyneb gwe rhagosodedig TOFU)</summary>
    <summary lang="da">(TOFU's standard webgrænseflade)</summary>
    <summary lang="de">(Standardwebinterface von TOFU)</summary>
    <summary lang="el">(Προεπιλεγμένη διεπαφή ιστού του TOFU)</summary>
    <summary lang="en">(TOFU's default web interface)</summary>
    <summary lang="en_AU">(TOFU's default web interface)</summary>
    <summary lang="en_NZ">(TOFU's default web interface)</summary>
    <summary lang="en_US">(TOFU's default web interface)</summary>
    <summary lang="es">(Interfaz web por defecto de TOFU)</summary>
    <summary lang="es_AR">(Interfaz web por defecto de TOFU)</summary>
    <summary lang="es_MX">(Interfaz Web por defecto de TOFU)</summary>
    <summary lang="et">(Vaikimisi keskkond)</summary>
    <summary lang="eu">(TOFU-ren lehenetsiriko web interfazea)</summary>
    <summary lang="fa">(رابط پیش فرض TOFU)</summary>
    <summary lang="fi">(TOFU:n oletus WWW-käyttöliittymä)</summary>
    <summary lang="fr">(Interface Web par défaut de TOFU)</summary>
    <summary lang="fr_CA">(Interface Web par défaut d'TOFU)</summary>
    <summary lang="gl">(Interface web predefinida de TOFU)</summary>
    <summary lang="he">(ברירת המחדל)</summary>
    <summary lang="hr">(TOFUjevo uobičajeno web sučelje)</summary>
    <summary lang="hu">(TOFU alapértelmezett webes kezelőfelülete)</summary>
    <summary lang="id">(Antar muka web bawaan TOFU)</summary>
    <summary lang="is">(Sjálfgefið vefviðmót á TOFU)</summary>
    <summary lang="it">(Interfaccia web di default per TOFU)</summary>
    <summary lang="ja">(TOFU's default web interface)</summary>
    <summary lang="ko">(TOFU 기본 웹 인터페이스)</summary>
    <summary lang="lt">(TOFU numatytoji žiniatinklio sąsaja)</summary>
    <summary lang="lv">(TOFU noklusētā tīmekļa saskarne)</summary>
    <summary lang="mk">(TOFU's подразбирачки веб интерфејс)</summary>
    <summary lang="ms">(antaramuka web lalai TOFU) </summary>
    <summary lang="my">(TOFU ၏ မူရင် ဝက်ဘ် အသွင်အပြင်)</summary>
    <summary lang="nl">(TOFU's standaard webinterface)</summary>
    <summary lang="no">(TOFUs standard nettgrensesnitt)</summary>
    <summary lang="pl">(Domyślny)</summary>
    <summary lang="pt">(Interface Web padrão do TOFU)</summary>
    <summary lang="pt_BR">(interface web padrão do TOFU)</summary>
    <summary lang="ro">(interfață web implicită pentru TOFU)</summary>
    <summary lang="ru">(веб-интерфейс TOFU по умолчанию).</summary>
    <summary lang="se">(TOFU's standardwebbgränssnitt)</summary>
    <summary lang="sk">(predvolené webové rozhranie pre TOFU)</summary>
    <summary lang="sl">(Privzet spletni vmesnik za TOFU)</summary>
    <summary lang="sr">(подразумевани веб интерфејс TOFU-а)</summary>
    <summary lang="sv">(TOFU's standardwebbgränssnitt)</summary>
    <summary lang="tg">(Интерфейси веби пешфарз барои TOFU)</summary>
    <summary lang="th">(ส่วนประสานหน้าเว็บพื้นฐานของ TOFU)</summary>
    <summary lang="tr">(TOFU'nin varsayılan web arayüzü)</summary>
    <summary lang="uk">(Типовий веб-інтерфейс  для TOFU)</summary>
    <summary lang="uz">(TOFU andoza veb interfeysi)</summary>
    <summary lang="vi">(Giao diện Web mặc định của TOFU)</summary>
    <summary lang="zh">（TOFU 的默认 web 界面）</summary>
    <summary lang="zh_TW">(TOFU的預設網頁介面)</summary>
    <description lang="af">Verstek web koppelvlak vir TOFU; Ontwerp vir toestelle van alle resolusies (Base: Team-Kodi Default web interface)</description>
    <description lang="am">ነባር የዌብ ገጽታዎች ለ TOFU ፡ የተነደፈው ለሁሉም አካላቶች resolutions ነው  (Base: Team-Kodi Default web interface)</description>
    <description lang="ar">واجهه الشبكة العنكبوتية المبدئية لـ توفو، مُصمَمة لتناسب كافة قياسات أبعاد الشاشات (Base: Team-Kodi Default web interface)</description>
    <description lang="be">Стандартны вэб-інтэрфэйс да TOFU; распрацаваны для прыладаў зь любымі разрознасьцямі (Base: Team-Kodi Default web interface)</description>
    <description lang="bg">Стандартния уеб интерфейс на TOFU; Направен е за устройства с най-различни резолюции (Base: Team-Kodi Default web interface)</description>
    <description lang="ca">Interfície web per defecte del TOFU; Dissenyada per dispositius de totes les resol·lucions (Base: Team-Kodi Default web interface)</description>
    <description lang="cs">Výchozí webové rozhraní TOFU navržené pro zařízení s libovolným rozlišením (Base: Team-Kodi Default web interface)</description>
    <description lang="cy">Rhyngwyneb gwe rhagosodedig TOFU. Wedi ei gynllunio ar gyfer cydraniad pob dyfais (Base: Team-Kodi Default web interface)</description>
    <description lang="da">Standard webgrænseflade til TOFU; designet til enheder i alle opløsninger (Base: Team-Kodi Default web interface)</description>
    <description lang="de">Standard TOFU Webinterface - Für alle Geräte und Auflösungen geeignet (Base: Team-Kodi Default web interface)</description>
    <description lang="el">Προεπιλεγμένη διεπαφή ιστού για το TOFU. Σχεδιασμένη για συσκευές όλων των αναλύσεων. (Base: Team-Kodi Default web interface)</description>
    <description lang="en">Default web interface for TOFU; Designed for devices of all resolutions (Base: Team-Kodi Default web interface)</description>
    <description lang="en_AU">Default web interface for TOFU; Designed for devices of all resolutions (Base: Team-Kodi Default web interface)</description>
    <description lang="en_NZ">Default web interface for TOFU; Designed for devices of all resolutions (Base: Team-Kodi Default web interface)</description>
    <description lang="en_US">Default web interface for TOFU; Designed for devices of all resolutions (Base: Team-Kodi Default web interface)</description>
    <description lang="es">Interfaz web por defecto de TOFU. Diseñada para dispositivos de cualquier resolución (Base: Team-Kodi Default web interface)</description>
    <description lang="es_AR">Interfaz web por defecto de TOFU. Diseñada para dispositivos de cualquier resolución (Base: Team-Kodi Default web interface)</description>
    <description lang="es_MX">Interfaz Web por defecto para TOFU; Diseñado para dispositivos de todas las resoluciones (Base: Team-Kodi Default web interface)</description>
    <description lang="et">TOFU vaikimisi veebikeskkond; Disainitud erinevate resolutsioonidega seadmetele. (Base: Team-Kodi Default web interface)</description>
    <description lang="eu">TOFU-ren lehenetsiriko web interfazea. Erresoluzio guztietako gailentzat diseinatua (Base: Team-Kodi Default web interface)</description>
    <description lang="fa">رابط پیش فرض TOFUوطراحی شده برای هر رزولیشن (Base: Team-Kodi Default web interface)</description>
    <description lang="fi">Oletus WWW-käyttöliittymä TOFU:lle. Suunniteltu käytettäväksi kaiken kokoisilla laitteilla. (Base: Team-Kodi Default web interface)</description>
    <description lang="fr">Interface Web par défaut de TOFU; Adaptée aux dispositifs de toutes résolutions (Base: Team-Kodi Default web interface)</description>
    <description lang="fr_CA">Interface Web par défaut d'TOFU - Conçue pour les dispositifs de toutes résolutions (Base: Team-Kodi Default web interface)</description>
    <description lang="gl">Interface web predefinida para TOFU, deseñada para dispositivos de todas as resolucións (Base: Team-Kodi Default web interface)</description>
    <description lang="he">ממשק דפדפן ברירת המחדל עבור TOFU; מותאם למכשירים בעלי אבחנות שונות (Base: Team-Kodi Default web interface)</description>
    <description lang="hr">Uobičajeno web sučelje za TOFU; Dizajnirano za uređaje svih razlučivosti (Base: Team-Kodi Default web interface)</description>
    <description lang="hu">Az TOFU alapértelmezett webes kezelőfelülete; Minden felbontásra alkalmas (Base: Team-Kodi Default web interface)</description>
    <description lang="hy">Նախնական տեսք TOFU-ի համար; Նախատեսված է բոլոր կրիչների համար (Base: Team-Kodi Default web interface)</description>
    <description lang="id">Antar muka web bawaan bagi TOFU; Dirancang bagi perangkat dengan semua resolusi (Base: Team-Kodi Default web interface)</description>
    <description lang="is">Sjálfgefið vefviðmót fyrir TOFU; Hannað fyrir tæki með allskonar upplausnir (Base: Team-Kodi Default web interface)</description>
    <description lang="it">Interfaccia Web di default per TOFU; Realizzata per periferiche con qualunque risoluzione (Base: Team-Kodi Default web interface)</description>
    <description lang="ja">TOFU のデフォルト Web インターフェースです。さまざまな解像度のデバイス用にデザインされています。 (Base: Team-Kodi Default web interface)</description>
    <description lang="ko">TOFU 기본 웹 인터페이스; 모든 해상도의 기기를 위해 디자인 됨 (Base: Team-Kodi Default web interface)</description>
    <description lang="lt">Numatytoji TOFU Web sąsaja skirta visų rezoliucijų prietaisams (Base: Team-Kodi Default web interface)</description>
    <description lang="lv">Noklusētā TOFU tīmekļa sakarne; Piemērota visu izšķirtspēju iekārtām (Base: Team-Kodi Default web interface)</description>
    <description lang="mk">Подразбирачки веб интерфејс за TOFU; Дизајниран за уреди со сите резолуции (Base: Team-Kodi Default web interface)</description>
    <description lang="ms">Antaramuka web lalai untuk TOFU; Di reka untuk peranti pelbagai resolusi (Base: Team-Kodi Default web interface)</description>
    <description lang="my">TOFU အတွက် မူရင်း ဝက်ဘ် အသွင်ပြင် ၊ စက်များ အားလုံး၏ resolutions အတွက် ရေးဆွဲထားသည်။ (Base: Team-Kodi Default web interface)</description>
    <description lang="nl">Standaard TOFU-webinterface; geschikt voor alle resoluties (Base: Team-Kodi Default web interface)</description>
    <description lang="no">Standard nettgrensesnitt for TOFU; Laget for alle oppløsninger (Base: Team-Kodi Default web interface)</description>
    <description lang="pl">Domyślny interfejs webowy TOFU; Zaprojektowany dla urządzeń o ekranach w dowolnej rozdzielczości (Base: Team-Kodi Default web interface)</description>
    <description lang="pt">Interface da Web predefinida do TOFU. Criada para dispositivos em qualquer resolução (Base: Team-Kodi Default web interface)</description>
    <description lang="pt_BR">Interface web padrão para TOFU; Concebida para dispositivos de todas as resoluções (Base: Team-Kodi Default web interface)</description>
    <description lang="ro">Interfață web implicită pentru TOFU, realizată de echipa TOFU pentru dispozitive cu orice rezoluție. (Base: Team-Kodi Default web interface)</description>
    <description lang="ru">Веб-интерфейс TOFU по умолчанию. Разработан для устройств с любыми разрешениями. (Base: Team-Kodi Default web interface)</description>
    <description lang="se">TOFU's standardwebbgränsnitt; Designat för alla upplösningar (Base: Team-Kodi Default web interface)</description>
    <description lang="si">TOFU' සඳහා නියත  වෙබ් අතුරුමුහුණත; සෑම විභේදනයකම උපකරණ සඳහා නිර්මාණය කර ඇත (Base: Team-Kodi Default web interface)</description>
    <description lang="sk">Predvolené webové rozhranie pre TOFU; Navrhnuté pre zariadenia zobrazujúce v akomkoľvek rozlíšení (Base: Team-Kodi Default web interface)</description>
    <description lang="sl">Privzet spletni vmesnik za TOFU, ustvarjen za naprave vseh ločljivosti (Base: Team-Kodi Default web interface)</description>
    <description lang="sr">Подразумевани веб интерфејс TOFU-а, намењен уређајима свих резолуција (Base: Team-Kodi Default web interface)</description>
    <description lang="sv">Standardwebbgränssnitt för TOFU; Utformat för alla enheter oavsett skärmupplösning (Base: Team-Kodi Default web interface)</description>
    <description lang="tg">Интерфейси веби пешфарз барои TOFU; Барои ҳар гуна дастгоҳ бо возеҳии экранаш гуногун эҷод карда шудааст (Base: Team-Kodi Default web interface)</description>
    <description lang="th">ส่วนประสานหน้าเว็บพื้นฐานสำหรับ TOFU ได้ออกแบบรองรับความละเอียดหน้าจอของอุปกรณ์ทั้งหมด (Base: Team-Kodi Default web interface)</description>
    <description lang="tr">TOFU için varsayılan web arayüzü; Bütün çözünürlüklerde tüm cihazlar için dizayn edilmiştir. (Base: Team-Kodi Default web interface)</description>
    <description lang="uk">Типовий веб-інтерфейс  для TOFU; Розроблений для пристроїв з будь-якою роздільною здатністю (Base: Team-Kodi Default web interface)</description>
    <description lang="uz">TOFU uchun andoza veb interfeysi; barcha ekran o'lchamlari bilan uskunalar uchun yaratilgan (Base: Team-Kodi Default web interface)</description>
    <description lang="vi">Giao diện Web mặc định cho TOFU; Thiết kế cho các thiết bị ở tất cả độ phân giải khác nhau (Base: Team-Kodi Default web interface)</description>
    <description lang="zh">TOFU 的默认 web 界面；为支持所有分辨率的设备而设计 (Base: Team-Kodi Default web interface)</description>
    <description lang="zh_TW">TOFU的預設網頁介面；針對所有解析度的設備而設計 (Base: Team-Kodi Default web interface)</description>
    <platform>all</platform>
  </extension>
</addon>
